kl_feishu/__init__.py
kl_feishu/feishu.py
kl_feishu/feishu_def.py
kl_feishu/feishu_server.py
kl_feishu/version.py
kl_feishu-0.0.19.dist-info/LICENSE
kl_feishu-0.0.19.dist-info/METADATA
kl_feishu-0.0.19.dist-info/WHEEL
kl_feishu-0.0.19.dist-info/top_level.txt
kl_feishu-0.0.19.dist-info/RECORD
